{
  "metadata" : {
    "realm" : "/",
    "entityType" : "OAuth2Provider",
    "entityId" : "defaultconfig",
    "uid" : "ou=defaultconfig,ou=OrganizationConfig,ou=1.0,ou=OAuth2Provider,ou=services,ou=am-config",
    "sunServiceID" : null,
    "objectClass" : [ "organizationalunit", "top", "sunServiceComponent" ],
    "pathParams" : { },
    "ou" : [ "defaultconfig" ]
  },
  "data" : {
    "_id" : "defaultconfig",
    "_type" : {
      "_id" : "OAuth2Provider",
      "name" : "OAuth2Provider",
      "collection" : false
    },
    "coreOIDCConfig" : {
      "supportedIDTokenSigningAlgorithms" : [ "PS384", "ES384", "RS384", "HS256", "HS512", "ES256", "RS256", "HS384", "ES512", "PS256", "PS512", "RS512" ],
      "supportedIDTokenEncryptionAlgorithms" : [ "ECDH-ES+A256KW", "ECDH-ES+A192KW", "RSA-OAEP", "ECDH-ES+A128KW", "RSA-OAEP-256", "A128KW", "A256KW", "ECDH-ES", "dir", "A192KW" ],
      "supportedIDTokenEncryptionMethods" : [ "A256GCM", "A192GCM", "A128GCM", "A128CBC-HS256", "A192CBC-HS384", "A256CBC-HS512" ],
      "supportedClaims" : [ ],
      "oidcClaimsScript" : null,
      "jwtTokenLifetime" : 3600
    },
    "cibaConfig" : {
      "supportedCibaSigningAlgorithms" : [ "ES256", "PS256" ],
      "cibaMinimumPollingInterval" : 2,
      "cibaAuthReqIdLifetime" : 600
    },
    "advancedOIDCConfig" : {
      "supportedTokenIntrospectionResponseSigningAlgorithms" : [ "PS384", "RS384", "EdDSA", "ES384", "HS256", "HS512", "ES256", "RS256", "HS384", "ES512", "PS256", "PS512", "RS512" ],
      "supportedRequestParameterSigningAlgorithms" : [ "PS384", "ES384", "RS384", "HS256", "HS512", "ES256", "RS256", "HS384", "ES512", "PS256", "PS512", "RS512" ],
      "supportedRequestParameterEncryptionAlgorithms" : [ "ECDH-ES+A256KW", "ECDH-ES+A192KW", "ECDH-ES+A128KW", "RSA-OAEP", "RSA-OAEP-256", "A128KW", "A256KW", "ECDH-ES", "dir", "A192KW" ],
      "defaultACR" : [ ],
      "supportedUserInfoEncryptionEnc" : [ "A256GCM", "A192GCM", "A128GCM", "A128CBC-HS256", "A192CBC-HS384", "A256CBC-HS512" ],
      "supportedUserInfoEncryptionAlgorithms" : [ "ECDH-ES+A256KW", "ECDH-ES+A192KW", "RSA-OAEP", "ECDH-ES+A128KW", "RSA-OAEP-256", "A128KW", "A256KW", "ECDH-ES", "dir", "A192KW" ],
      "supportedRequestParameterEncryptionEnc" : [ "A256GCM", "A192GCM", "A128GCM", "A128CBC-HS256", "A192CBC-HS384", "A256CBC-HS512" ],
      "storeOpsTokens" : true,
      "supportedTokenIntrospectionResponseEncryptionEnc" : [ "A256GCM", "A192GCM", "A128GCM", "A128CBC-HS256", "A192CBC-HS384", "A256CBC-HS512" ],
      "supportedTokenIntrospectionResponseEncryptionAlgorithms" : [ "ECDH-ES+A256KW", "ECDH-ES+A192KW", "RSA-OAEP", "ECDH-ES+A128KW", "RSA-OAEP-256", "A128KW", "A256KW", "ECDH-ES", "dir", "A192KW" ],
      "supportedTokenEndpointAuthenticationSigningAlgorithms" : [ "PS384", "ES384", "RS384", "HS256", "HS512", "ES256", "RS256", "HS384", "ES512", "PS256", "PS512", "RS512" ],
      "supportedUserInfoSigningAlgorithms" : [ "ES384", "HS256", "HS512", "ES256", "RS256", "HS384", "ES512" ],
      "idTokenInfoClientAuthenticationEnabled" : true,
      "alwaysAddClaimsToToken" : false,
      "jkwsURI" : null,
      "authorisedOpenIdConnectSSOClients" : [ ],
      "loaMapping" : { },
      "amrMappings" : { },
      "authorisedIdmDelegationClients" : [ ],
      "claimsParameterSupported" : false
    },
    "consent" : {
      "supportedRcsRequestEncryptionMethods" : [ "A256GCM", "A192GCM", "A128GCM", "A128CBC-HS256", "A192CBC-HS384", "A256CBC-HS512" ],
      "supportedRcsRequestSigningAlgorithms" : [ "PS384", "ES384", "RS384", "HS256", "HS512", "ES256", "RS256", "HS384", "ES512", "PS256", "PS512", "RS512" ],
      "supportedRcsResponseEncryptionAlgorithms" : [ "ECDH-ES+A256KW", "ECDH-ES+A192KW", "ECDH-ES+A128KW", "RSA-OAEP", "RSA-OAEP-256", "A128KW", "A256KW", "ECDH-ES", "dir", "A192KW" ],
      "supportedRcsResponseSigningAlgorithms" : [ "PS384", "ES384", "RS384", "HS256", "HS512", "ES256", "RS256", "HS384", "ES512", "PS256", "PS512", "RS512" ],
      "supportedRcsResponseEncryptionMethods" : [ "A256GCM", "A192GCM", "A128GCM", "A128CBC-HS256", "A192CBC-HS384", "A256CBC-HS512" ],
      "savedConsentAttribute" : null,
      "supportedRcsRequestEncryptionAlgorithms" : [ "ECDH-ES+A256KW", "ECDH-ES+A192KW", "RSA-OAEP", "ECDH-ES+A128KW", "RSA-OAEP-256", "A128KW", "A256KW", "ECDH-ES", "dir", "A192KW" ],
      "enableRemoteConsent" : false,
      "clientsCanSkipConsent" : false,
      "remoteConsentServiceId" : null
    },
    "advancedOAuth2Config" : {
      "tlsOcspResponderUri" : null,
      "responseTypeClasses" : [ "code|org.forgerock.oauth2.core.AuthorizationCodeResponseTypeHandler", "device_code|org.forgerock.oauth2.core.TokenResponseTypeHandler", "token|org.forgerock.oauth2.core.TokenResponseTypeHandler", "id_token|org.forgerock.oauth2.core.TokenResponseTypeHandler" ],
      "grantTypes" : [ "implicit", "urn:ietf:params:oauth:grant-type:saml2-bearer", "refresh_token", "password", "client_credentials", "urn:ietf:params:oauth:grant-type:device_code", "authorization_code", "urn:openid:params:grant-type:ciba", "urn:ietf:params:oauth:grant-type:uma-ticket", "urn:ietf:params:oauth:grant-type:jwt-bearer" ],
      "modifiedTimestampAttribute" : null,
      "displayNameAttribute" : "cn",
      "tlsCertificateRevocationCheckingEnabled" : false,
      "codeVerifierEnforced" : "false",
      "allowedAudienceValues" : [ ],
      "supportedScopes" : [ ],
      "moduleMessageEnabledInPasswordGrant" : false,
      "tokenEncryptionEnabled" : false,
      "tokenCompressionEnabled" : false,
      "supportedSubjectTypes" : [ "public" ],
      "passwordGrantAuthService" : null,
      "defaultScopes" : [ ],
      "tlsClientCertificateTrustedHeader" : null,
      "tlsClientCertificateHeaderFormat" : "URLENCODED_PEM",
      "authenticationAttributes" : [ "uid" ],
      "customLoginUrlTemplate" : null,
      "hashSalt" : "&{am.oidc.client.subject.identifier.hash.salt}",
      "createdTimestampAttribute" : null,
      "scopeImplementationClass" : "org.forgerock.openam.oauth2.OpenAMScopeValidator",
      "macaroonTokenFormat" : "V2",
      "tlsCertificateBoundAccessTokensEnabled" : true,
      "tokenSigningAlgorithm" : "HS256",
      "tlsOcspResponderCert" : null
    },
    "coreOAuth2Config" : {
      "issueRefreshTokenOnRefreshedToken" : true,
      "issueRefreshToken" : true,
      "macaroonTokensEnabled" : false,
      "statelessTokensEnabled" : false,
      "refreshTokenLifetime" : 604800,
      "accessTokenModificationScript" : null,
      "usePolicyEngineForScope" : false,
      "codeLifetime" : 120,
      "accessTokenLifetime" : 3600
    },
    "deviceCodeConfig" : {
      "deviceCodeLifetime" : 300,
      "verificationUrl" : null,
      "completionUrl" : null,
      "devicePollInterval" : 5
    },
    "ListValueValidator" : "com.sun.identity.common.configuration.ListValueValidator",
    "clientDynamicRegistrationConfig" : {
      "generateRegistrationAccessTokens" : true,
      "dynamicClientRegistrationSoftwareStatementRequired" : false,
      "dynamicClientRegistrationScope" : "dynamic_client_registration",
      "requiredSoftwareStatementAttestedAttributes" : [ "redirect_uris" ],
      "allowDynamicRegistration" : false
    },
    "MapValueValidator" : "com.sun.identity.common.configuration.MapValueValidator",
    "RequiredValueValidator" : "com.sun.identity.sm.RequiredValueValidator"
  }
}
