{
  "metadata" : {
    "realm" : null,
    "entityType" : "sunIdentityRepositoryService",
    "entityId" : "default/role",
    "uid" : "ou=role,ou=default,ou=GlobalConfig,ou=1.0,ou=sunIdentityRepositoryService,ou=services,ou=am-config",
    "sunServiceID" : "SupportedIdentities",
    "objectClass" : [ "top", "sunServiceComponent" ],
    "pathParams" : { },
    "ou" : null
  },
  "data" : {
    "_id" : "default/role",
    "_type" : {
      "_id" : "sunIdentityRepositoryService",
      "name" : "sunIdentityRepositoryService",
      "collection" : false
    },
    "canAddMembers" : [ "user" ],
    "canHaveMembers" : [ "user" ]
  }
}
