{
  "metadata" : {
    "realm" : "/",
    "entityType" : "iPlanetAMAuthWindowsDesktopSSOService",
    "entityId" : "defaultconfig",
    "uid" : "ou=defaultconfig,ou=OrganizationConfig,ou=1.0,ou=iPlanetAMAuthWindowsDesktopSSOService,ou=services,ou=am-config",
    "sunServiceID" : null,
    "objectClass" : [ "organizationalunit", "top", "sunServiceComponent" ],
    "pathParams" : { },
    "ou" : null
  },
  "data" : {
    "_id" : "defaultconfig",
    "_type" : {
      "_id" : "iPlanetAMAuthWindowsDesktopSSOService",
      "name" : "iPlanetAMAuthWindowsDesktopSSOService",
      "collection" : false
    },
    "keytabFileName" : null,
    "trustedKerberosRealms" : [ ],
    "kerberosServerName" : null,
    "kerberosServiceIsinitiator" : true,
    "kerberosRealm" : null,
    "principalName" : null,
    "returnPrincipalWithDomainName" : false,
    "lookupUserInRealm" : false,
    "authenticationLevel" : 0
  }
}
